LICENSE
MANIFEST.in
README.rst
setup.cfg
setup.py
django_markdownme.egg-info/PKG-INFO
django_markdownme.egg-info/SOURCES.txt
django_markdownme.egg-info/dependency_links.txt
django_markdownme.egg-info/requires.txt
django_markdownme.egg-info/top_level.txt
markdownme/__init__.py
markdownme/admin.py
markdownme/apps.py
markdownme/fields.py
markdownme/models.py
markdownme/settings.py
markdownme/urls.py
markdownme/views.py
markdownme/widgets.py
markdownme/migrations/0001_initial.py
markdownme/migrations/__init__.py
markdownme/static/markdownme/css/dropzone.min.css
markdownme/static/markdownme/css/markdownme.min.css
markdownme/static/markdownme/js/diff.min.js
markdownme/static/markdownme/js/dropzone.min.js
markdownme/static/markdownme/js/markdownme.min.js
markdownme/templates/markdownme/textedit.html