Metadata-Version: 1.1
Name: django-markdownme
Version: 0.1
Summary: A Django text editor with Markdown and file upload support
Home-page: https://github.com/oliverkovac/django-markdownme
Author: Oliver Kovac
Author-email: oliver.kovac.2@student.tuke.sk
License: MIT License
Platform: UNKNOWN
Classifier: Environment :: Web Environment
Classifier: Framework :: Django
Classifier: Framework :: Django :: 1.10
Classifier: Intended Audience :: Developers
Classifier: License :: OSI Approved :: MIT License
Classifier: Operating System :: OS Independent
Classifier: Programming Language :: Python
Classifier: Programming Language :: Python :: 3
Classifier: Programming Language :: Python :: 3.4
Classifier: Programming Language :: Python :: 3.5
Classifier: Topic :: Internet :: WWW/HTTP
Classifier: Topic :: Internet :: WWW/HTTP :: Dynamic Content
